haggis/__init__.py
haggis/args.py
haggis/configuration.py
haggis/ctypes_util.py
haggis/exceptions.py
haggis/latex_util.py
haggis/load.py
haggis/logs.py
haggis/mapping.py
haggis/math.py
haggis/mpl_util.py
haggis/npy_util.py
haggis/numbers.py
haggis/objects.py
haggis/os.py
haggis/recipes.py
haggis/string_util.py
haggis/structures.py
haggis/threads.py
haggis/time.py
haggis/version.py
haggis/files/__init__.py
haggis/files/csv.py
haggis/files/docx.py
haggis/files/fits.py
haggis/files/pdf.py
haggis/files/ps.py
haggis/files/ui.py
haggis/files/xlsx.py
haggis/files/xml.py
haggis/files/zip.py
haggis/files/_resources/MML2OMML.XSL
haggis/files/tests/__init__.py
haggis/files/tests/test_csv.py
haggis/gui/__init__.py
haggis/gui/qt.py
haggis/tests/__init__.py
haggis/tests/conftest.py
haggis/tests/options.py
haggis/tests/test_args.py
haggis/tests/test_load.py
haggis/tests/test_logs.py
haggis/tests/test_math.py
haggis/tests/test_npy_util.py
haggis/tests/test_numbers.py
haggis/tests/test_objects.py
haggis/tests/test_recipes.py
haggis/tests/test_string_util.py
haggis/tests/util.py
haggis/tests/data/bfs_module_0.txt
haggis/tests/data/bfs_module_1.txt
haggis/tests/data/bfs_module_2.txt
haggis/tests/data/bfs_module_3.txt
haggis/tests/data/injection_module.txt
haggis/tests/data/module.txt
haggis/tests/data/nested_injection_module.txt
haggis/tests/data/nested_module.txt
haggis-0.14.1.data/data/CHANGELOG
haggis-0.14.1.data/data/LICENSE
haggis-0.14.1.data/data/README.md
haggis-0.14.1.dist-info/LICENSE
haggis-0.14.1.dist-info/METADATA
haggis-0.14.1.dist-info/WHEEL
haggis-0.14.1.dist-info/top_level.txt
haggis-0.14.1.dist-info/RECORD
