Metadata-Version: 2.1
Name: haggis
Version: 0.14.1
Summary: General purpose utility library
Home-page: https://gitlab.com/madphysicist/haggis
Author: Joseph R. Fox-Rabinovitz
Author-email: jfoxrabinovitz@gmail.com
Maintainer: Joseph R. Fox-Rabinovitz
Maintainer-email: jfoxrabinovitz@gmail.com
License: GNU Affero General Public License v3 or later (AGPLv3+)
Project-URL: Bugs, https://gitlab.com/madphysicist/haggis/-/issues
Project-URL: Documentation, https://haggis.readthedocs.io/en/stable/
Platform: UNKNOWN
Classifier: Development Status :: 2 - Pre-Alpha
Classifier: Intended Audience :: Developers
Classifier: Intended Audience :: Other Audience
Classifier: License :: OSI Approved :: GNU Affero General Public License v3 or later (AGPLv3+)
Classifier: Operating System :: Microsoft :: Windows
Classifier: Operating System :: POSIX :: Linux
Classifier: Operating System :: Unix
Classifier: Programming Language :: Python
Classifier: Programming Language :: Python :: 3 :: Only
Classifier: Programming Language :: Python :: 3.6
Classifier: Programming Language :: Python :: 3.7
Classifier: Programming Language :: Python :: 3.8
Classifier: Programming Language :: Python :: 3.9
Classifier: Programming Language :: Python :: 3.10
Classifier: Programming Language :: Python :: 3.10
Classifier: Programming Language :: Python :: 3.11
Classifier: Programming Language :: Python :: 3.12
Classifier: Topic :: Software Development :: Libraries
Classifier: Topic :: System :: Console Fonts
Classifier: Topic :: System :: Logging
Classifier: Topic :: Terminals
Classifier: Topic :: Text Processing
Classifier: Topic :: Text Processing :: General
Classifier: Topic :: Text Processing :: Markup
Classifier: Topic :: Text Processing :: Markup :: LaTeX
Classifier: Topic :: Text Processing :: Markup :: XML
Classifier: Topic :: Utilities
Provides: haggis
License-File: LICENSE
Requires-Dist: numpy >=1.10
Provides-Extra: all
Requires-Dist: astropy >=3.0 ; extra == 'all'
Requires-Dist: matplotlib >=1.5 ; extra == 'all'
Requires-Dist: openpyxl >=2.4.8 ; extra == 'all'
Requires-Dist: python-docx >=0.8.5 ; extra == 'all'
Requires-Dist: scipy >0.16 ; extra == 'all'
Requires-Dist: colorama >=0.3 ; (platform_system == "Windows") and extra == 'all'
Provides-Extra: docx
Requires-Dist: python-docx >=0.8.5 ; extra == 'docx'
Provides-Extra: latex
Provides-Extra: pdf
Provides-Extra: plot
Requires-Dist: matplotlib >=1.5 ; extra == 'plot'
Provides-Extra: ps
Provides-Extra: qt
Requires-Dist: PyQt6 ; extra == 'qt'
Provides-Extra: scio
Requires-Dist: astropy >=3.0 ; extra == 'scio'
Requires-Dist: scipy >0.16 ; extra == 'scio'
Provides-Extra: term
Requires-Dist: colorama >=0.3 ; (platform_system == "Windows") and extra == 'term'
Provides-Extra: xlsx
Requires-Dist: openpyxl >=2.4.8 ; extra == 'xlsx'
